[
  {
    "tag_name": "entity",
    "ids_to_tags": {
      "1": "B-count",
      "2": "I-count",
      "3": "L-count",
      "4": "U-count",
      "5": "B-p_count",
      "6": "I-p_count",
      "7": "L-p_count",
      "8": "U-p_count",
      "9": "B-service",
      "10": "I-service",
      "11": "L-service",
      "12": "U-service",
      "13": "B-sevice",
      "14": "I-sevice",
      "15": "L-sevice",
      "16": "U-sevice",
      "0": "O"
    },
    "tags_to_ids": {
      "B-count": 1,
      "I-count": 2,
      "L-count": 3,
      "U-count": 4,
      "B-p_count": 5,
      "I-p_count": 6,
      "L-p_count": 7,
      "U-p_count": 8,
      "B-service": 9,
      "I-service": 10,
      "L-service": 11,
      "U-service": 12,
      "B-sevice": 13,
      "I-sevice": 14,
      "L-sevice": 15,
      "U-sevice": 16,
      "O": 0
    },
    "num_tags": 17
  }
]